mkdocs_print_site_plugin/__init__.py
mkdocs_print_site_plugin/exclude.py
mkdocs_print_site_plugin/plugin.py
mkdocs_print_site_plugin/renderer.py
mkdocs_print_site_plugin/urls.py
mkdocs_print_site_plugin/utils.py
mkdocs_print_site_plugin/css/print-site-material.css
mkdocs_print_site_plugin/css/print-site-mkdocs.css
mkdocs_print_site_plugin/css/print-site-readthedocs.css
mkdocs_print_site_plugin/css/print-site.css
mkdocs_print_site_plugin/js/print-site.js
mkdocs_print_site_plugin/templates/cover_page.tpl
mkdocs_print_site_plugin/templates/print_site_banner.tpl
mkdocs_print_site_plugin-2.7.3.dist-info/licenses/LICENSE
mkdocs_print_site_plugin-2.7.3.dist-info/METADATA
mkdocs_print_site_plugin-2.7.3.dist-info/WHEEL
mkdocs_print_site_plugin-2.7.3.dist-info/entry_points.txt
mkdocs_print_site_plugin-2.7.3.dist-info/top_level.txt
mkdocs_print_site_plugin-2.7.3.dist-info/RECORD
