Metadata-Version: 2.4
Name: mkdocs-print-site-plugin
Version: 2.7.3
Summary: MkDocs plugin that combines all pages into one, allowing for easy export to PDF and standalone HTML.
Author-email: Tim Vink <vinktim@gmail.com>
License: MIT
Project-URL: Homepage, https://github.com/timvink/mkdocs-print-site-plugin
Keywords: mkdocs,plugin,print,pdf
Classifier: Operating System :: OS Independent
Classifier: Programming Language :: Python
Classifier: Programming Language :: Python :: 3
Classifier: Programming Language :: Python :: 3.8
Classifier: Programming Language :: Python :: 3.9
Classifier: Programming Language :: Python :: 3.10
Classifier: Programming Language :: Python :: 3.11
Classifier: License :: OSI Approved :: MIT License
Classifier: Topic :: Documentation
Classifier: Topic :: Text Processing
Requires-Python: >=3.8
License-File: LICENSE
Requires-Dist: mkdocs-material>=7.3.0
Dynamic: license-file
